setup.cfg
setup.py
beholder_sdk/__init__.py
beholder_sdk/main.py
beholder_sdk.egg-info/PKG-INFO
beholder_sdk.egg-info/SOURCES.txt
beholder_sdk.egg-info/dependency_links.txt
beholder_sdk.egg-info/top_level.txt
beholder_sdk/database/__init__.py
beholder_sdk/database/db_connector.py
beholder_sdk/database/models.py
beholder_sdk/middleware/__init__.py
beholder_sdk/middleware/django_middleware.py
beholder_sdk/middleware/fastapi_middleware.py
beholder_sdk/middleware/flask_middleware.py
beholder_sdk/services/__init__.py
beholder_sdk/services/collector.py